mltb/__init__.py
mltb/hyperopt.py
mltb/keras.py
mltb/lightgbm.py
mltb/metrics.py
mltb/pdtb.py
mltb/plot.py
mltb/shap.py
mltb/tensorflow.py
mltb/tools.py
mltb/version.py
mltb-0.8.0.dist-info/LICENSE
mltb-0.8.0.dist-info/METADATA
mltb-0.8.0.dist-info/WHEEL
mltb-0.8.0.dist-info/top_level.txt
mltb-0.8.0.dist-info/RECORD
