Metadata-Version: 2.1
Name: mltb
Version: 0.8.0
Summary: Machine Learning Tool Box
Home-page: https://github.com/PhilipMay/mltb
Author: Philip May
Author-email: pm@eniak.de
Maintainer: Philip May
License: UNKNOWN
Keywords: keras metric hyperopt lightgbm plot visualisation
Platform: UNKNOWN
Classifier: Development Status :: 3 - Alpha
Classifier: Intended Audience :: Education
Classifier: Intended Audience :: Science/Research
Classifier: Intended Audience :: Developers
Classifier: Programming Language :: Python :: 3
Classifier: Topic :: Scientific/Engineering
Classifier: Topic :: Software Development
Classifier: License :: OSI Approved :: BSD License
Classifier: Operating System :: OS Independent
Requires-Python: >=3.6
Requires-Dist: sklearn
Requires-Dist: numpy
Requires-Dist: matplotlib
Requires-Dist: pandas
Requires-Dist: tqdm
Requires-Dist: scipy
Requires-Dist: joblib
Provides-Extra: checking
Requires-Dist: black ; extra == 'checking'
